run_scripts/__init__.py
run_scripts/cli.py
run_scripts/command.py
run_scripts/commands/init.py
run_scripts/commands/run.py
run_scripts/group.py
run_scripts/listener.py
run_scripts/style.py
run_scripts-0.1.2.dist-info/entry_points.txt
run_scripts-0.1.2.dist-info/WHEEL
run_scripts-0.1.2.dist-info/METADATA
run_scripts-0.1.2.dist-info/RECORD
