Metadata-Version: 2.1
Name: run-scripts
Version: 0.1.2
Summary: A CLI for running npm-like scripts
Home-page: https://github.com/keksiqc/run-cli
Author: Keksi
Author-email: contact@keksi.me
Requires-Python: >=3.10,<4.0
Classifier: Programming Language :: Python :: 3
Classifier: Programming Language :: Python :: 3.10
Requires-Dist: PyYAML (>=6.0,<7.0)
Requires-Dist: click (>=8.1.3,<9.0.0)
Project-URL: Repository, https://github.com/keksiqc/run-cli
